kakao_json/__init__.py
kakao_json/components/__init__.py
kakao_json/components/cards.py
kakao_json/components/common.py
kakao_json/kakao.py
kakao_json-1.0.4.dist-info/LICENSE
kakao_json-1.0.4.dist-info/METADATA
kakao_json-1.0.4.dist-info/WHEEL
kakao_json-1.0.4.dist-info/RECORD
