Metadata-Version: 2.1
Name: kakao_json
Version: 1.0.4
Summary: 카카오챗봇 JSON helper
License: MIT
Author: Seok Won
Author-email: ikr@kakao.com
Requires-Python: >=3.10,<4.0
Classifier: License :: OSI Approved :: MIT License
Classifier: Programming Language :: Python :: 3
Classifier: Programming Language :: Python :: 3.10
Classifier: Programming Language :: Python :: 3.11
Classifier: Programming Language :: Python :: 3.12
Requires-Dist: msgspec (>=0.18.6,<0.19.0)
